mcp_google_cse/__init__.py
mcp_google_cse/__main__.py
mcp_google_cse/server.py
mseep_mcp_google_cse-0.1.8.dist-info/licenses/LICENSE
mseep_mcp_google_cse-0.1.8.dist-info/METADATA
mseep_mcp_google_cse-0.1.8.dist-info/WHEEL
mseep_mcp_google_cse-0.1.8.dist-info/entry_points.txt
mseep_mcp_google_cse-0.1.8.dist-info/top_level.txt
mseep_mcp_google_cse-0.1.8.dist-info/RECORD
